mdmodels/__init__.py
mdmodels/adder_method.py
mdmodels/create.py
mdmodels/datamodel.py
mdmodels/git_utils.py
mdmodels/graph/__init__.py
mdmodels/graph/basenode.py
mdmodels/graph/create.py
mdmodels/graph/relation.py
mdmodels/library.py
mdmodels/llm/__init__.py
mdmodels/llm/embed.py
mdmodels/llm/fetcher.py
mdmodels/llm/handler.py
mdmodels/llm/prompts.py
mdmodels/llm/response.py
mdmodels/llm/templates/__init__.py
mdmodels/llm/templates/dataset_query.py
mdmodels/meta.py
mdmodels/path.py
mdmodels/reference.py
mdmodels/sql/__init__.py
mdmodels/sql/base.py
mdmodels/sql/connector.py
mdmodels/sql/create.py
mdmodels/sql/insert.py
mdmodels/sql/linked_type.py
mdmodels/sql/utils.py
mdmodels/templates.py
mdmodels/units/__init__.py
mdmodels/units/annotation.py
mdmodels/units/converter.py
mdmodels/units/mappings.py
mdmodels/units/unit_definition.py
mdmodels/utils.py
mdmodels-0.2.4.dist-info/METADATA
mdmodels-0.2.4.dist-info/WHEEL
mdmodels-0.2.4.dist-info/RECORD
