Metadata-Version: 2.4
Name: mdmodels
Version: 0.2.4
Summary: Python package for the MDModels Rust crate
Author: Jan Range
Author-email: range.jan@web.de
Requires-Python: >=3.11,<4.0
Classifier: Programming Language :: Python :: 3
Classifier: Programming Language :: Python :: 3.11
Classifier: Programming Language :: Python :: 3.12
Classifier: Programming Language :: Python :: 3.13
Classifier: Programming Language :: Python :: 3.14
Provides-Extra: chat
Provides-Extra: dev
Provides-Extra: graph
Provides-Extra: sql
Requires-Dist: astropy (>=7.2.0,<8.0.0)
Requires-Dist: bigtree (>=0.21.1,<0.22.0)
Requires-Dist: dotted-dict (>=1.1.3,<2.0.0)
Requires-Dist: httpx (>=0.28,<0.29)
Requires-Dist: instructor (>=1.7.0,<2.0.0) ; extra == "chat"
Requires-Dist: mdmodels-core (>=0.2.7,<0.3.0)
Requires-Dist: neomodel (>=5.4.0,<6.0.0) ; extra == "graph"
Requires-Dist: nest-asyncio (>=1.6.0,<2.0.0)
Requires-Dist: openai (>=1.57.0,<2.0.0) ; extra == "chat"
Requires-Dist: pandas (==2.2.3)
Requires-Dist: pydantic-xml (>=2.12.1,<3.0.0)
Requires-Dist: python-forge (>=18.6.0,<19.0.0)
Requires-Dist: python-jsonpath (>=1.2.0,<2.0.0)
Requires-Dist: rich (>=13.9.4,<14.0.0)
Requires-Dist: sqlmodel (>=0.0.22,<0.0.23) ; extra == "sql"
Requires-Dist: tabulate (>=0.9.0,<0.10.0) ; extra == "chat"
Requires-Dist: validators (>=0.34.0,<0.35.0)
